reed_solomon_leopard-0.2.1.dist-info/METADATA
reed_solomon_leopard-0.2.1.dist-info/WHEEL
reed_solomon_leopard-0.2.1.dist-info/licenses/LICENSE
reed_solomon_leopard/__init__.py
reed_solomon_leopard/reed_solomon_leopard.cpython-39-x86_64-linux-gnu.so
reed_solomon_leopard-0.2.1.dist-info/RECORD
