Metadata-Version: 2.3
Name: reed-solomon-leopard
Version: 0.2.1
Classifier: Programming Language :: Rust
Classifier: Programming Language :: Python :: Implementation :: CPython
Classifier: Programming Language :: Python :: Implementation :: PyPy
License-File: LICENSE
Summary: Fast Reed-Solomon library. Up to 65535 original or recovery shards
Requires-Python: >=3.8
Project-URL: repository, https://github.com/AndersTrier/reed-solomon-leopard
